rocm_wsl_ai/__init__.py
rocm_wsl_ai/cli.py
rocm_wsl_ai/core/base.py
rocm_wsl_ai/core/comfy.py
rocm_wsl_ai/core/config.py
rocm_wsl_ai/core/models.py
rocm_wsl_ai/core/models_download.py
rocm_wsl_ai/core/models_index.py
rocm_wsl_ai/core/process.py
rocm_wsl_ai/core/utils.py
rocm_wsl_ai/core/venv.py
rocm_wsl_ai/scripts/installers.py
rocm_wsl_ai/tools/image.py
rocm_wsl_ai/tools/llm.py
rocm_wsl_ai/tui/app.py
rocm_wsl_ai/tui/dialogs.py
rocm_wsl_ai/tui/models.py
rocm_wsl_ai/web/app.py
rocm_wsl_ai/web/static/app.css
rocm_wsl_ai/web/static/app.js
rocm_wsl_ai/web/templates/first_run.html
rocm_wsl_ai/web/templates/help.html
rocm_wsl_ai/web/templates/index.html
rocm_wsl_ai/web/templates/login.html
rocm_wsl_ai/web/templates/models.html
rocm_wsl_ai/web/templates/tools.html
rocm_wsl_ai/web/templates/wizard.html
rocm_wsl_ai/web/templates/partials/tool_card.html
rocm_wsl_ai-0.2.10.dist-info/licenses/LICENSE
rocm_wsl_ai-0.2.10.dist-info/METADATA
rocm_wsl_ai-0.2.10.dist-info/WHEEL
rocm_wsl_ai-0.2.10.dist-info/entry_points.txt
rocm_wsl_ai-0.2.10.dist-info/top_level.txt
rocm_wsl_ai-0.2.10.dist-info/RECORD
