Metadata-Version: 2.4
Name: rocm-wsl-ai
Version: 0.2.10
Summary: Web UI to install and manage AMD ROCm + local AI tools on WSL2 (with optional CLI/TUI)
Author: daMustermann
License-Expression: MIT
Project-URL: Homepage, https://github.com/daMustermann/rocm-wsl-ai
Project-URL: Repository, https://github.com/daMustermann/rocm-wsl-ai
Project-URL: Issues, https://github.com/daMustermann/rocm-wsl-ai/issues
Keywords: rocm,wsl,amd,fastapi,webui,stable-diffusion,llm,comfyui,ollama,textgen
Classifier: Development Status :: 4 - Beta
Classifier: Environment :: Web Environment
Classifier: Intended Audience :: End Users/Desktop
Classifier: Operating System :: POSIX :: Linux
Classifier: Programming Language :: Python
Classifier: Programming Language :: Python :: 3
Classifier: Programming Language :: Python :: 3 :: Only
Classifier: Programming Language :: Python :: 3.10
Classifier: Programming Language :: Python :: 3.11
Classifier: Topic :: Internet :: WWW/HTTP
Classifier: Topic :: System :: Systems Administration
Requires-Python: >=3.10
License-File: LICENSE
Requires-Dist: typer>=0.12.0
Requires-Dist: rich>=13.7.0
Requires-Dist: textual>=0.58.0
Requires-Dist: tomli>=2.0.1; python_version < "3.11"
Requires-Dist: fastapi>=0.111.0
Requires-Dist: uvicorn[standard]>=0.30.0
Requires-Dist: jinja2>=3.1.4
Requires-Dist: python-multipart>=0.0.7
Dynamic: license-file
